{"bones":[{"name":"root","x":-636.74,"y":-345.26},{"name":"bone6","parent":"root","length":314.71,"x":726.91,"y":174.03,"rotation":-3.17}],"slots":[{"name":"btn2","bone":"bone6","attachment":"12"}],"skins":{"default":{"btn2":{"8":{"x":157.12,"y":3.61,"rotation":3.17,"width":394,"height":120},"9":{"x":157.12,"y":3.61,"rotation":3.17,"width":394,"height":120},"10":{"x":157.12,"y":3.61,"rotation":3.17,"width":394,"height":120},"11":{"x":157.12,"y":3.61,"rotation":3.17,"width":394,"height":120},"12":{"x":157.12,"y":3.61,"rotation":3.17,"width":394,"height":120},"13":{"x":157.12,"y":3.61,"rotation":3.17,"width":394,"height":120},"14":{"x":157.12,"y":3.61,"rotation":3.17,"width":394,"height":120}}}},"animations":{"animation":{"slots":{"btn2":{"attachment":[{"time":0,"name":"14"},{"time":0.1666,"name":"8"},{"time":0.2333,"name":"9"},{"time":0.3,"name":"10"},{"time":0.3666,"name":"11"},{"time":0.4333,"name":"12"},{"time":0.5,"name":"13"},{"time":1.3333,"name":"14"}]}}}}}